{"frames": {

"CombatCyborg.jpg":
{
	"frame": {"x":0,"y":0,"w":689,"h":507},
	"rotated": false,
	"trimmed": false,
	"spriteSourceSize": {"x":0,"y":0,"w":689,"h":507},
	"sourceSize": {"w":689,"h":507}
},
"FSCContinuanceWanderer.jpg":
{
	"frame": {"x":692,"y":0,"w":680,"h":988},
	"rotated": false,
	"trimmed": false,
	"spriteSourceSize": {"x":0,"y":0,"w":680,"h":988},
	"sourceSize": {"w":680,"h":988}
},
"HeartOfTheWanderer.jpg":
{
	"frame": {"x":1375,"y":0,"w":689,"h":507},
	"rotated": false,
	"trimmed": false,
	"spriteSourceSize": {"x":0,"y":0,"w":689,"h":507},
	"sourceSize": {"w":689,"h":507}
},
"ParadoxIntrusion.jpg":
{
	"frame": {"x":2067,"y":0,"w":689,"h":507},
	"rotated": false,
	"trimmed": false,
	"spriteSourceSize": {"x":0,"y":0,"w":689,"h":507},
	"sourceSize": {"w":689,"h":507}
},
"PrehistoricBehemoth.jpg":
{
	"frame": {"x":2759,"y":0,"w":689,"h":507},
	"rotated": false,
	"trimmed": false,
	"spriteSourceSize": {"x":0,"y":0,"w":689,"h":507},
	"sourceSize": {"w":689,"h":507}
},
"SuperimposedRealities.jpg":
{
	"frame": {"x":0,"y":991,"w":689,"h":507},
	"rotated": false,
	"trimmed": false,
	"spriteSourceSize": {"x":0,"y":0,"w":689,"h":507},
	"sourceSize": {"w":689,"h":507}
},
"TemporalAcceleration.jpg":
{
	"frame": {"x":692,"y":991,"w":689,"h":507},
	"rotated": false,
	"trimmed": false,
	"spriteSourceSize": {"x":0,"y":0,"w":689,"h":507},
	"sourceSize": {"w":689,"h":507}
},
"TemporalReset.jpg":
{
	"frame": {"x":1384,"y":991,"w":689,"h":507},
	"rotated": false,
	"trimmed": false,
	"spriteSourceSize": {"x":0,"y":0,"w":689,"h":507},
	"sourceSize": {"w":689,"h":507}
},
"TemporalReversal.jpg":
{
	"frame": {"x":2076,"y":991,"w":689,"h":507},
	"rotated": false,
	"trimmed": false,
	"spriteSourceSize": {"x":0,"y":0,"w":689,"h":507},
	"sourceSize": {"w":689,"h":507}
},
"TemporalSlipstream.jpg":
{
	"frame": {"x":2768,"y":991,"w":689,"h":507},
	"rotated": false,
	"trimmed": false,
	"spriteSourceSize": {"x":0,"y":0,"w":689,"h":507},
	"sourceSize": {"w":689,"h":507}
},
"TimeFreeze.jpg":
{
	"frame": {"x":0,"y":1501,"w":689,"h":507},
	"rotated": false,
	"trimmed": false,
	"spriteSourceSize": {"x":0,"y":0,"w":689,"h":507},
	"sourceSize": {"w":689,"h":507}
},
"VortexGlitch.jpg":
{
	"frame": {"x":692,"y":1501,"w":689,"h":507},
	"rotated": false,
	"trimmed": false,
	"spriteSourceSize": {"x":0,"y":0,"w":689,"h":507},
	"sourceSize": {"w":689,"h":507}
},
"VortexInterference.jpg":
{
	"frame": {"x":1384,"y":1501,"w":689,"h":507},
	"rotated": false,
	"trimmed": false,
	"spriteSourceSize": {"x":0,"y":0,"w":689,"h":507},
	"sourceSize": {"w":689,"h":507}
},
"VortexSurge.jpg":
{
	"frame": {"x":2076,"y":1501,"w":689,"h":507},
	"rotated": false,
	"trimmed": false,
	"spriteSourceSize": {"x":0,"y":0,"w":689,"h":507},
	"sourceSize": {"w":689,"h":507}
}},
"meta": {
	"app": "https://www.codeandweb.com/texturepacker",
	"version": "1.0",
	"image": "FSCContinuanceWandererAtlas0.png",
	"format": "RGBA8888",
	"size": {"w":4096,"h":4096},
	"scale": "1",
	"smartupdate": "$TexturePacker:SmartUpdate:66a343e1438ffca006cddb492e4414dc:62a5350776759ab98a1134f643add5d7:0123c114b05cfcbbc0a1cf263dfeb698$"
}
}
