{"frames": {

"AclastyphWhoPeers.png":
{
	"frame": {"x":0,"y":991,"w":689,"h":507},
	"rotated": false,
	"trimmed": false,
	"spriteSourceSize": {"x":0,"y":0,"w":689,"h":507},
	"sourceSize": {"w":689,"h":507}
},
"ClockworkRevenant.png":
{
	"frame": {"x":692,"y":991,"w":689,"h":507},
	"rotated": false,
	"trimmed": false,
	"spriteSourceSize": {"x":0,"y":0,"w":689,"h":507},
	"sourceSize": {"w":689,"h":507}
},
"DangerousInvestigation.png":
{
	"frame": {"x":1384,"y":991,"w":689,"h":507},
	"rotated": false,
	"trimmed": false,
	"spriteSourceSize": {"x":0,"y":0,"w":689,"h":507},
	"sourceSize": {"w":689,"h":507}
},
"DoktorVonFaust.png":
{
	"frame": {"x":2076,"y":991,"w":689,"h":507},
	"rotated": false,
	"trimmed": false,
	"spriteSourceSize": {"x":0,"y":0,"w":689,"h":507},
	"sourceSize": {"w":689,"h":507}
},
"FaithfulProselyte.png":
{
	"frame": {"x":2768,"y":991,"w":689,"h":507},
	"rotated": false,
	"trimmed": false,
	"spriteSourceSize": {"x":0,"y":0,"w":689,"h":507},
	"sourceSize": {"w":689,"h":507}
},
"HallucinatedHorror.png":
{
	"frame": {"x":0,"y":1501,"w":689,"h":507},
	"rotated": false,
	"trimmed": false,
	"spriteSourceSize": {"x":0,"y":0,"w":689,"h":507},
	"sourceSize": {"w":689,"h":507}
},
"MythosCharacter.png":
{
	"frame": {"x":0,"y":0,"w":680,"h":988},
	"rotated": false,
	"trimmed": false,
	"spriteSourceSize": {"x":0,"y":0,"w":680,"h":988},
	"sourceSize": {"w":680,"h":988}
},
"MythosCharacterBack.png":
{
	"frame": {"x":683,"y":0,"w":680,"h":988},
	"rotated": false,
	"trimmed": false,
	"spriteSourceSize": {"x":0,"y":0,"w":680,"h":988},
	"sourceSize": {"w":680,"h":988}
},
"MythosEyeDeckBack.png":
{
	"frame": {"x":1366,"y":0,"w":680,"h":988},
	"rotated": false,
	"trimmed": false,
	"spriteSourceSize": {"x":0,"y":0,"w":680,"h":988},
	"sourceSize": {"w":680,"h":988}
},
"MythosFearDeckBack.png":
{
	"frame": {"x":2049,"y":0,"w":680,"h":988},
	"rotated": false,
	"trimmed": false,
	"spriteSourceSize": {"x":0,"y":0,"w":680,"h":988},
	"sourceSize": {"w":680,"h":988}
},
"MythosMindDeckBack.png":
{
	"frame": {"x":2732,"y":0,"w":680,"h":988},
	"rotated": false,
	"trimmed": false,
	"spriteSourceSize": {"x":0,"y":0,"w":680,"h":988},
	"sourceSize": {"w":680,"h":988}
},
"OtherworldlyAlignment.png":
{
	"frame": {"x":692,"y":1501,"w":689,"h":507},
	"rotated": false,
	"trimmed": false,
	"spriteSourceSize": {"x":0,"y":0,"w":689,"h":507},
	"sourceSize": {"w":689,"h":507}
},
"PallidAcademic.png":
{
	"frame": {"x":1384,"y":1501,"w":689,"h":507},
	"rotated": false,
	"trimmed": false,
	"spriteSourceSize": {"x":0,"y":0,"w":689,"h":507},
	"sourceSize": {"w":689,"h":507}
},
"PreyUponTheMind.png":
{
	"frame": {"x":2076,"y":1501,"w":689,"h":507},
	"rotated": false,
	"trimmed": false,
	"spriteSourceSize": {"x":0,"y":0,"w":689,"h":507},
	"sourceSize": {"w":689,"h":507}
},
"Revelations.png":
{
	"frame": {"x":2768,"y":1501,"w":689,"h":507},
	"rotated": false,
	"trimmed": false,
	"spriteSourceSize": {"x":0,"y":0,"w":689,"h":507},
	"sourceSize": {"w":689,"h":507}
},
"RitualSite.png":
{
	"frame": {"x":0,"y":2011,"w":689,"h":507},
	"rotated": false,
	"trimmed": false,
	"spriteSourceSize": {"x":0,"y":0,"w":689,"h":507},
	"sourceSize": {"w":689,"h":507}
},
"RustedArtifact.png":
{
	"frame": {"x":692,"y":2011,"w":689,"h":507},
	"rotated": false,
	"trimmed": false,
	"spriteSourceSize": {"x":0,"y":0,"w":689,"h":507},
	"sourceSize": {"w":689,"h":507}
},
"TornPage.png":
{
	"frame": {"x":1384,"y":2011,"w":689,"h":507},
	"rotated": false,
	"trimmed": false,
	"spriteSourceSize": {"x":0,"y":0,"w":689,"h":507},
	"sourceSize": {"w":689,"h":507}
},
"WhispersAndLies.png":
{
	"frame": {"x":2076,"y":2011,"w":689,"h":507},
	"rotated": false,
	"trimmed": false,
	"spriteSourceSize": {"x":0,"y":0,"w":689,"h":507},
	"sourceSize": {"w":689,"h":507}
},
"YourDarkestSecrets.png":
{
	"frame": {"x":2768,"y":2011,"w":689,"h":507},
	"rotated": false,
	"trimmed": false,
	"spriteSourceSize": {"x":0,"y":0,"w":689,"h":507},
	"sourceSize": {"w":689,"h":507}
}},
"meta": {
	"app": "https://www.codeandweb.com/texturepacker",
	"version": "1.0",
	"image": "MythosAtlas0.png",
	"format": "RGBA8888",
	"size": {"w":4096,"h":4096},
	"scale": "1",
	"smartupdate": "$TexturePacker:SmartUpdate:e4cbdd01c7aa43d8a0eaaca0e4c7eae4:6f0d6e7f19148fab5cd57d7c51901e08:aa4b40754777d861fb3ba8d47267ba43$"
}
}
