{"frames": {

"ChameleonArmor.jpg":
{
	"frame": {"x":2049,"y":991,"w":689,"h":507},
	"rotated": false,
	"trimmed": false,
	"spriteSourceSize": {"x":0,"y":0,"w":689,"h":507},
	"sourceSize": {"w":689,"h":507}
},
"CreedOfTheSniperTangoOne.png":
{
	"frame": {"x":679,"y":0,"w":680,"h":988},
	"rotated": false,
	"trimmed": false,
	"spriteSourceSize": {"x":0,"y":0,"w":680,"h":988},
	"sourceSize": {"w":680,"h":988}
},
"CreedOfTheSniperTangoOneBack.png":
{
	"frame": {"x":1362,"y":0,"w":680,"h":988},
	"rotated": false,
	"trimmed": false,
	"spriteSourceSize": {"x":0,"y":0,"w":680,"h":988},
	"sourceSize": {"w":680,"h":988}
},
"CriticalHit.jpg":
{
	"frame": {"x":2741,"y":991,"w":689,"h":507},
	"rotated": false,
	"trimmed": false,
	"spriteSourceSize": {"x":0,"y":0,"w":689,"h":507},
	"sourceSize": {"w":689,"h":507}
},
"DamnGoodGround.jpg":
{
	"frame": {"x":0,"y":1982,"w":689,"h":507},
	"rotated": false,
	"trimmed": false,
	"spriteSourceSize": {"x":0,"y":0,"w":689,"h":507},
	"sourceSize": {"w":689,"h":507}
},
"DisablingShot.jpg":
{
	"frame": {"x":692,"y":1982,"w":689,"h":507},
	"rotated": false,
	"trimmed": false,
	"spriteSourceSize": {"x":0,"y":0,"w":689,"h":507},
	"sourceSize": {"w":689,"h":507}
},
"Farsight.jpg":
{
	"frame": {"x":1384,"y":1982,"w":689,"h":507},
	"rotated": false,
	"trimmed": false,
	"spriteSourceSize": {"x":0,"y":0,"w":689,"h":507},
	"sourceSize": {"w":689,"h":507}
},
"GhostOpsTangoOneCharacter.jpg":
{
	"frame": {"x":2045,"y":0,"w":680,"h":988},
	"rotated": false,
	"trimmed": false,
	"spriteSourceSize": {"x":0,"y":0,"w":680,"h":988},
	"sourceSize": {"w":680,"h":988}
},
"GhostOpsTangoOneCharacterBack.jpg":
{
	"frame": {"x":2728,"y":0,"w":680,"h":988},
	"rotated": false,
	"trimmed": false,
	"spriteSourceSize": {"x":0,"y":0,"w":680,"h":988},
	"sourceSize": {"w":680,"h":988}
},
"GhostReactor.jpg":
{
	"frame": {"x":2076,"y":1982,"w":689,"h":507},
	"rotated": false,
	"trimmed": false,
	"spriteSourceSize": {"x":0,"y":0,"w":689,"h":507},
	"sourceSize": {"w":689,"h":507}
},
"Infiltrate.jpg":
{
	"frame": {"x":2768,"y":1982,"w":689,"h":507},
	"rotated": false,
	"trimmed": false,
	"spriteSourceSize": {"x":0,"y":0,"w":689,"h":507},
	"sourceSize": {"w":689,"h":507}
},
"LineEmUp.jpg":
{
	"frame": {"x":0,"y":2492,"w":689,"h":507},
	"rotated": false,
	"trimmed": false,
	"spriteSourceSize": {"x":0,"y":0,"w":689,"h":507},
	"sourceSize": {"w":689,"h":507}
},
"OneShotOneKill.jpg":
{
	"frame": {"x":692,"y":2492,"w":689,"h":507},
	"rotated": false,
	"trimmed": false,
	"spriteSourceSize": {"x":0,"y":0,"w":689,"h":507},
	"sourceSize": {"w":689,"h":507}
},
"Opportunist.jpg":
{
	"frame": {"x":1384,"y":2492,"w":689,"h":507},
	"rotated": false,
	"trimmed": false,
	"spriteSourceSize": {"x":0,"y":0,"w":689,"h":507},
	"sourceSize": {"w":689,"h":507}
},
"PastTangoOneCharacter.png":
{
	"frame": {"x":3411,"y":0,"w":680,"h":988},
	"rotated": false,
	"trimmed": false,
	"spriteSourceSize": {"x":0,"y":0,"w":680,"h":988},
	"sourceSize": {"w":680,"h":988}
},
"PastTangoOneCharacterBack.png":
{
	"frame": {"x":0,"y":991,"w":680,"h":988},
	"rotated": false,
	"trimmed": false,
	"spriteSourceSize": {"x":0,"y":0,"w":680,"h":988},
	"sourceSize": {"w":680,"h":988}
},
"PerfectFocus.jpg":
{
	"frame": {"x":2076,"y":2492,"w":689,"h":507},
	"rotated": false,
	"trimmed": false,
	"spriteSourceSize": {"x":0,"y":0,"w":689,"h":507},
	"sourceSize": {"w":689,"h":507}
},
"PsionicSuppression.jpg":
{
	"frame": {"x":2768,"y":2492,"w":689,"h":507},
	"rotated": false,
	"trimmed": false,
	"spriteSourceSize": {"x":0,"y":0,"w":689,"h":507},
	"sourceSize": {"w":689,"h":507}
},
"SniperRifle.jpg":
{
	"frame": {"x":0,"y":3002,"w":689,"h":507},
	"rotated": false,
	"trimmed": false,
	"spriteSourceSize": {"x":0,"y":0,"w":689,"h":507},
	"sourceSize": {"w":689,"h":507}
},
"TangoOneCharacter.jpg":
{
	"frame": {"x":683,"y":991,"w":680,"h":988},
	"rotated": false,
	"trimmed": false,
	"spriteSourceSize": {"x":0,"y":0,"w":680,"h":988},
	"sourceSize": {"w":680,"h":988}
},
"TangoOneCharacterBack.jpg":
{
	"frame": {"x":1366,"y":991,"w":680,"h":988},
	"rotated": false,
	"trimmed": false,
	"spriteSourceSize": {"x":0,"y":0,"w":680,"h":988},
	"sourceSize": {"w":680,"h":988}
},
"TangoOneDeckBack.jpg":
{
	"frame": {"x":0,"y":0,"w":676,"h":979},
	"rotated": false,
	"trimmed": false,
	"spriteSourceSize": {"x":0,"y":0,"w":676,"h":979},
	"sourceSize": {"w":676,"h":979}
},
"WetWork.jpg":
{
	"frame": {"x":692,"y":3002,"w":689,"h":507},
	"rotated": false,
	"trimmed": false,
	"spriteSourceSize": {"x":0,"y":0,"w":689,"h":507},
	"sourceSize": {"w":689,"h":507}
}},
"meta": {
	"app": "https://www.codeandweb.com/texturepacker",
	"version": "1.0",
	"image": "TangoOneAtlas0.png",
	"format": "RGBA8888",
	"size": {"w":4096,"h":4096},
	"scale": "1",
	"smartupdate": "$TexturePacker:SmartUpdate:ac3f55ef53fe8394227637bd091a6648:7651a78ea31939d50066651c5cbf6b93:da2592f3ad57ae4f0c9fd14880ed964c$"
}
}
